llama_index/packs/deeplake_multimodal_retrieval/__init__.py
llama_index/packs/deeplake_multimodal_retrieval/base.py
llama_index_packs_deeplake_multimodal_retrieval-0.3.0.dist-info/METADATA
llama_index_packs_deeplake_multimodal_retrieval-0.3.0.dist-info/WHEEL
llama_index_packs_deeplake_multimodal_retrieval-0.3.0.dist-info/licenses/LICENSE
llama_index_packs_deeplake_multimodal_retrieval-0.3.0.dist-info/RECORD
