Metadata-Version: 2.4
Name: llama-index-packs-deeplake-multimodal-retrieval
Version: 0.3.0
Summary: llama-index packs deeplake_multimodal_retrieval integration
Author-email: Your Name <you@example.com>
Maintainer: AdkSarsen
License-Expression: MIT
License-File: LICENSE
Keywords: deeplake,multimodal,retriever
Requires-Python: <4.0,>=3.9
Requires-Dist: llama-index-core<0.14,>=0.13.0
Requires-Dist: llama-index-vector-stores-deeplake<0.5,>=0.4.0
